pytest-approxable/__init__.py
pytest_approxable/__init__.py
hackinteach_pytest_approxable-0.0.3.dist-info/LICENSE
hackinteach_pytest_approxable-0.0.3.dist-info/METADATA
hackinteach_pytest_approxable-0.0.3.dist-info/WHEEL
hackinteach_pytest_approxable-0.0.3.dist-info/top_level.txt
hackinteach_pytest_approxable-0.0.3.dist-info/RECORD
