Metadata-Version: 2.1
Name: hackinteach-pytest-approxable
Version: 0.0.3
Summary: A pytest approxable dict mixin for data class
Home-page: https://github.com/hackinteach/pytest-approxable
Author: hackinteach
Author-email: webmaster@hackinteach.com
License: UNKNOWN
Platform: UNKNOWN
Classifier: Programming Language :: Python :: 3
Classifier: License :: OSI Approved :: Apache Software License
Classifier: Operating System :: OS Independent
Requires-Python: >=3.7
